{"ongoing_trials": {}, "hyperparameters": {"space": [{"class_name": "Int", "config": {"name": "na", "default": null, "conditions": [], "min_value": 64, "max_value": 512, "step": 64, "sampling": "linear"}}, {"class_name": "Int", "config": {"name": "nb", "default": null, "conditions": [], "min_value": 128, "max_value": 1024, "step": 128, "sampling": "linear"}}, {"class_name": "Float", "config": {"name": "dropout_rate", "default": 0.1, "conditions": [], "min_value": 0.1, "max_value": 0.5, "step": 0.1, "sampling": "linear"}}, {"class_name": "Float", "config": {"name": "l2_reg", "default": 1e-06, "conditions": [], "min_value": 1e-06, "max_value": 0.01, "step": null, "sampling": "log"}}, {"class_name": "Float", "config": {"name": "learning_rate", "default": 0.0001, "conditions": [], "min_value": 0.0001, "max_value": 0.01, "step": null, "sampling": "log"}}, {"class_name": "Float", "config": {"name": "weight_decay", "default": 1e-07, "conditions": [], "min_value": 1e-07, "max_value": 0.001, "step": null, "sampling": "log"}}, {"class_name": "Int", "config": {"name": "local_dem_units", "default": null, "conditions": [], "min_value": 32, "max_value": 256, "step": 32, "sampling": "linear"}}, {"class_name": "Int", "config": {"name": "regional_dem_units", "default": null, "conditions": [], "min_value": 32, "max_value": 256, "step": 32, "sampling": "linear"}}, {"class_name": "Int", "config": {"name": "month_units", "default": null, "conditions": [], "min_value": 16, "max_value": 128, "step": 16, "sampling": "linear"}}, {"class_name": "Int", "config": {"name": "climate_units", "default": null, "conditions": [], "min_value": 64, "max_value": 512, "step": 64, "sampling": "linear"}}, {"class_name": "Boolean", "config": {"name": "use_residual", "default": false, "conditions": []}}, {"class_name": "Choice", "config": {"name": "activation", "default": "relu", "conditions": [], "values": ["relu", "elu", "selu"], "ordered": false}}, {"class_name": "Choice", "config": {"name": "output_activation", "default": "relu", "conditions": [], "values": ["relu", "softplus"], "ordered": false}}], "values": {"na": 64, "nb": 128, "dropout_rate": 0.1, "l2_reg": 1e-06, "learning_rate": 0.0001, "weight_decay": 1e-07, "local_dem_units": 32, "regional_dem_units": 32, "month_units": 16, "climate_units": 64, "use_residual": false, "activation": "relu", "output_activation": "relu"}}, "start_order": ["00", "01", "02", "03", "04", "05", "06", "07", "08", "09", "10", "011", "012", "013", "014", "015", "016", "017", "018", "019", "020", "021", "022", "023", "024", "025", "026", "027", "028", "029", "030", "031", "032", "033", "034", "035", "036", "037", "038", "039", "040", "041", "042", "043", "044", "045", "046", "047", "048", "049", "050", "051", "052", "053", "054", "055", "056", "057", "058", "059", "060", "061", "062", "063", "064", "065", "066", "067", "068", "069", "070", "071", "072", "073", "074", "075", "076", "077", "078", "079", "080", "081", "082", "083", "084", "085", "086", "087", "088", "089", "090", "091", "092", "093", "094", "095", "096", "097", "098", "099"], "end_order": ["00", "01", "02", "03", "04", "05", "06", "07", "08", "09", "10", "011", "012", "013", "014", "015", "016", "017", "018", "019", "020", "021", "022", "023", "024", "025", "026", "027", "028", "029", "030", "031", "032", "033", "034", "035", "036", "037", "038", "039", "040", "041", "042", "043", "044", "045", "046", "047", "048", "049", "050", "051", "052", "053", "054", "055", "056", "057", "058", "059", "060", "061", "062", "063", "064", "065", "066", "067", "068", "069", "070", "071", "072", "073", "074", "075", "076", "077", "078", "079", "080", "081", "082", "083", "084", "085", "086", "087", "088", "089", "090", "091", "092", "093", "094", "095", "096", "097", "098", "099"], "run_times": {"00": 1, "01": 1, "02": 1, "03": 1, "04": 1, "05": 1, "06": 1, "07": 1, "08": 1, "09": 1, "10": 1, "011": 1, "012": 1, "013": 1, "014": 1, "015": 1, "016": 1, "017": 1, "018": 1, "019": 1, "020": 1, "021": 1, "022": 1, "023": 1, "024": 1, "025": 1, "026": 1, "027": 1, "028": 1, "029": 1, "030": 1, "031": 1, "032": 1, "033": 1, "034": 1, "035": 1, "036": 1, "037": 1, "038": 1, "039": 1, "040": 1, "041": 1, "042": 1, "043": 1, "044": 1, "045": 1, "046": 1, "047": 1, "048": 1, "049": 1, "050": 1, "051": 1, "052": 1, "053": 1, "054": 1, "055": 1, "056": 1, "057": 1, "058": 1, "059": 1, "060": 1, "061": 1, "062": 1, "063": 1, "064": 1, "065": 1, "066": 1, "067": 1, "068": 1, "069": 1, "070": 1, "071": 1, "072": 1, "073": 1, "074": 1, "075": 1, "076": 1, "077": 1, "078": 1, "079": 1, "080": 1, "081": 1, "082": 1, "083": 1, "084": 1, "085": 1, "086": 1, "087": 1, "088": 1, "089": 1, "090": 1, "091": 1, "092": 1, "093": 1, "094": 1, "095": 1, "096": 1, "097": 1, "098": 1, "099": 1}, "retry_queue": [], "seed": 7574, "seed_state": 8094, "tried_so_far": ["bcbf1c706ae1e618b8c6348771b7f1f4", "5ccdef40e9e4e62a8d7c11d777879bf3", "464112b7eb268de08710462c01ede01b", "82f0d4b3ceed21e24aba4eb69f29b502", "22d67ee5adacbbd573f83323263d9665", "ebbc98018371c5d9fad42cc2f324e381", "1fd61cfcb761ebb3b463630f855cd161", "fb68447cff414d3e8ed1f01d1cd741ef", "63de8d14c57804bd24280b51cb21f87c", "f699e4339addba67dca270d152a3d10a", "0432f80ed76e98fe50d2dedaa4730d15", "0f41cac9e3579a8b98c7fa6be25805aa", "e6d270a1ef57d25bf2d173385bc74a1e", "76bb1d11e70b696fd92300efd29d122c", "98aa0acfbc7b5501dd642211d64bdfb3", "50c4b9e1f753da005f2dce7217159435", "655a7f9967179b4c376d059653b4cf30", "72be709120d1f51b17bd81b0717019e7", "11af9edd230a3c8309b7992a9f590d65", "813eeeca00a40696cc6d8d7dec8428c6", "46fbd6f7e7474b5acbe2fcdd95d43391", "ad055a910e79125e9a1e519044ee2794", "530cc12806839e329e59ea2651bb6008", "8020417f13186ac6f59177a9f5e30a09", "b373ced76c8e4166bc7d751bee986244", "7cdc4dc67864ee31bb5528e3e470d9ba", "e637908673b7ddfe5379c548251c3399", "c3f75eb85af8ca259bace68b9592c1cd", "23c99fb33ced53be5156be2dd3324ce1", "0728ac825990334f2b5b6d2ad19cf331", "7aec03dfb8e105e3512276c4e8278df1", "f91a06bb1f5aab17ed8e5ca77520977c", "06eb35acb980eb35054545eadef587dc", "7c6c76194f52ad13112dde97b2f41674", "ace93d7119c58ce50711a3d3645032e0", "aad2bcbb225bee980b5ac80e28b38370", "9f7fa8ea182b817a9b2441e768126c4e", "9bf0c190bc07b66bea3dbdde165c1d22", "694748e8b17d9693e0b21c16cf4d59e9", "84a72902cb3518d3d387c08ca07e5458", "5763b4eba286a560a71f534342ddd672", "4ca4a7dfb74f2245595d5619ade7e24b", "91762850cfa654200061b76f01c8694c", "3b93b32e850bbed56217180a1d7456ae", "a8db557ed963ca218eef38871487883a", "690697d72806aced3a280e1c3ac20981", "a5e53fb38aa55e09f1cc11377de49cc8", "1c72f7a150f28f1e4973e8579e834ae3", "a1f1677e10b0bb00901abb22b01a8725", "7bda9d8664090c498f8b85818ac79d3a", "d3e1d3ec925fbd5e70450e6b05ed3457", "5800d0415349ca9ca8bdddb6dbb191ad", "40c58a7b0a73d03de1517032a71b968f", "e4e5a5ce566e8f570292de5ac5ad49df", "1d09c77ce2466822b90d0aaefc23c2ee", "c4b99631912cae9f903a535ba8281616", "8b1fc5ee65d72770dbc72935f7c7a389", "99354cbafae4f74e5d65ac8f8840eda9", "26941b550c97db1d168cd4a5e939fd9f", "d61aa7dbe625a9eeacb33dd1e02884f8", "cd319041f9a9eb00634ac977a6826212", "236bdfd497250f93a878365f3fce587e", "01ff3e389644a00cabe5f420a4ce383f", "e2516436f197c553f2b1b8d81510fc14", "c722c90f3041c3d73174fc6ed2ed6476", "89e77750427435f706d7379491252597", "333e975d5c40bd196d751696ea474275", "a68282c2695c8324d306b2bd3dbe5258", "0b9c6a1072e57599d81a173397945810", "103a1688da368538309678359e210901", "8fce1d79ca0b009c5795885ccde234ed", "85dd913ec5bdb2f1198d0b6f455d2b97", "dab1d7af7be0d0ad900895ba6fec47cf", "e7ec57edf4fb02b3b0aff395956d272f", "8938666dcf173c0b403893cacd2ba0ac", "32ffadaf5aa9743a071ae395b6a0f59e", "9ab58243f9c51a96d4ff9ff66e15af8e", "39d15967e8b55dd4944a513461c1376b", "d9f9fead8d7928f4b331be567ecfc099", "458988dd97667bbfbfdfe1a75d416a63", "eec6c2d4f240a7c466380d7393fbe1bb", "c5ed3b2363b27ca84ce2f50c8a59190d", "ef7800af59365c0ecaf47b4da046aa4f", "d688e5aa707ff8522ffa44a693368cc2", "e7b09a612fbd6731cce55bc45598b32e", "f70b13761e36c40f1a5400dc6cc6a183", "85c3fc8858bb3fb384e6f176a0d63f4f", "cd73c0cb2375cda8b6fda4827e5fa3cd", "1e070edecf6c19c90939ad97c9dfc418", "fec9778568cd2e6928133e729a1589dd", "17ede7c469530b4140c3a91592f1dd92", "787c04f4292ad24bca60d278fb9513f4", "a94e2ed611a4715fc63a6b608642ef59", "1cd3a6a38445b530518ac2e72203b752", "8a21060ee847580cc41d30e6849a0118", "851ebc8f46d35c60d8f1b25a2c5320f1", "0a55d31517dc23b6a6cc59a21b275e26", "c2ea3dffe192b6c5619fe994f370669e", "4f3fbace5194ce4b4ddbd7330b26354b", "662da00dedb27fb749274739aeffd369"], "id_to_hash": {"00": "103a1688da368538309678359e210901", "01": "82f0d4b3ceed21e24aba4eb69f29b502", "02": "b373ced76c8e4166bc7d751bee986244", "03": "fec9778568cd2e6928133e729a1589dd", "04": "662da00dedb27fb749274739aeffd369", "05": "f699e4339addba67dca270d152a3d10a", "06": "5800d0415349ca9ca8bdddb6dbb191ad", "07": "f70b13761e36c40f1a5400dc6cc6a183", "08": "1d09c77ce2466822b90d0aaefc23c2ee", "09": "e2516436f197c553f2b1b8d81510fc14", "10": "98aa0acfbc7b5501dd642211d64bdfb3", "011": "d9f9fead8d7928f4b331be567ecfc099", "012": "17ede7c469530b4140c3a91592f1dd92", "013": "655a7f9967179b4c376d059653b4cf30", "014": "aad2bcbb225bee980b5ac80e28b38370", "015": "e637908673b7ddfe5379c548251c3399", "016": "c4b99631912cae9f903a535ba8281616", "017": "3b93b32e850bbed56217180a1d7456ae", "018": "fb68447cff414d3e8ed1f01d1cd741ef", "019": "4f3fbace5194ce4b4ddbd7330b26354b", "020": "4ca4a7dfb74f2245595d5619ade7e24b", "021": "ef7800af59365c0ecaf47b4da046aa4f", "022": "8a21060ee847580cc41d30e6849a0118", "023": "bcbf1c706ae1e618b8c6348771b7f1f4", "024": "e4e5a5ce566e8f570292de5ac5ad49df", "025": "89e77750427435f706d7379491252597", "026": "9f7fa8ea182b817a9b2441e768126c4e", "027": "1cd3a6a38445b530518ac2e72203b752", "028": "99354cbafae4f74e5d65ac8f8840eda9", "029": "813eeeca00a40696cc6d8d7dec8428c6", "030": "cd319041f9a9eb00634ac977a6826212", "031": "0432f80ed76e98fe50d2dedaa4730d15", "032": "787c04f4292ad24bca60d278fb9513f4", "033": "236bdfd497250f93a878365f3fce587e", "034": "46fbd6f7e7474b5acbe2fcdd95d43391", "035": "ace93d7119c58ce50711a3d3645032e0", "036": "464112b7eb268de08710462c01ede01b", "037": "7cdc4dc67864ee31bb5528e3e470d9ba", "038": "85c3fc8858bb3fb384e6f176a0d63f4f", "039": "7bda9d8664090c498f8b85818ac79d3a", "040": "9bf0c190bc07b66bea3dbdde165c1d22", "041": "5ccdef40e9e4e62a8d7c11d777879bf3", "042": "0b9c6a1072e57599d81a173397945810", "043": "1fd61cfcb761ebb3b463630f855cd161", "044": "72be709120d1f51b17bd81b0717019e7", "045": "dab1d7af7be0d0ad900895ba6fec47cf", "046": "ad055a910e79125e9a1e519044ee2794", "047": "f91a06bb1f5aab17ed8e5ca77520977c", "048": "1c72f7a150f28f1e4973e8579e834ae3", "049": "c722c90f3041c3d73174fc6ed2ed6476", "050": "a68282c2695c8324d306b2bd3dbe5258", "051": "7aec03dfb8e105e3512276c4e8278df1", "052": "8fce1d79ca0b009c5795885ccde234ed", "053": "e6d270a1ef57d25bf2d173385bc74a1e", "054": "32ffadaf5aa9743a071ae395b6a0f59e", "055": "d61aa7dbe625a9eeacb33dd1e02884f8", "056": "c3f75eb85af8ca259bace68b9592c1cd", "057": "85dd913ec5bdb2f1198d0b6f455d2b97", "058": "e7b09a612fbd6731cce55bc45598b32e", "059": "a5e53fb38aa55e09f1cc11377de49cc8", "060": "8020417f13186ac6f59177a9f5e30a09", "061": "26941b550c97db1d168cd4a5e939fd9f", "062": "22d67ee5adacbbd573f83323263d9665", "063": "d3e1d3ec925fbd5e70450e6b05ed3457", "064": "694748e8b17d9693e0b21c16cf4d59e9", "065": "9ab58243f9c51a96d4ff9ff66e15af8e", "066": "d688e5aa707ff8522ffa44a693368cc2", "067": "06eb35acb980eb35054545eadef587dc", "068": "23c99fb33ced53be5156be2dd3324ce1", "069": "8b1fc5ee65d72770dbc72935f7c7a389", "070": "84a72902cb3518d3d387c08ca07e5458", "071": "c2ea3dffe192b6c5619fe994f370669e", "072": "a1f1677e10b0bb00901abb22b01a8725", "073": "851ebc8f46d35c60d8f1b25a2c5320f1", "074": "e7ec57edf4fb02b3b0aff395956d272f", "075": "1e070edecf6c19c90939ad97c9dfc418", "076": "7c6c76194f52ad13112dde97b2f41674", "077": "39d15967e8b55dd4944a513461c1376b", "078": "01ff3e389644a00cabe5f420a4ce383f", "079": "690697d72806aced3a280e1c3ac20981", "080": "0f41cac9e3579a8b98c7fa6be25805aa", "081": "50c4b9e1f753da005f2dce7217159435", "082": "11af9edd230a3c8309b7992a9f590d65", "083": "ebbc98018371c5d9fad42cc2f324e381", "084": "cd73c0cb2375cda8b6fda4827e5fa3cd", "085": "5763b4eba286a560a71f534342ddd672", "086": "eec6c2d4f240a7c466380d7393fbe1bb", "087": "a94e2ed611a4715fc63a6b608642ef59", "088": "a8db557ed963ca218eef38871487883a", "089": "91762850cfa654200061b76f01c8694c", "090": "458988dd97667bbfbfdfe1a75d416a63", "091": "530cc12806839e329e59ea2651bb6008", "092": "333e975d5c40bd196d751696ea474275", "093": "8938666dcf173c0b403893cacd2ba0ac", "094": "40c58a7b0a73d03de1517032a71b968f", "095": "c5ed3b2363b27ca84ce2f50c8a59190d", "096": "76bb1d11e70b696fd92300efd29d122c", "097": "0728ac825990334f2b5b6d2ad19cf331", "098": "0a55d31517dc23b6a6cc59a21b275e26", "099": "63de8d14c57804bd24280b51cb21f87c"}, "display": {"search_start": "2025-05-20T13:40:24.640115", "trial_start": {"00": "2025-05-20T13:40:24.640115", "01": "2025-05-20T13:42:29.716003", "02": "2025-05-20T13:44:28.386914", "03": "2025-05-20T13:45:21.470486", "04": "2025-05-20T13:47:12.083549", "05": "2025-05-20T13:48:22.445024", "06": "2025-05-20T13:49:55.300135", "07": "2025-05-20T13:50:57.891136", "08": "2025-05-20T13:52:02.425284", "09": "2025-05-20T13:53:34.061837", "10": "2025-05-20T13:56:43.565494", "011": "2025-05-20T13:57:24.784940", "012": "2025-05-20T13:59:06.621961", "013": "2025-05-20T14:00:50.204201", "014": "2025-05-20T14:01:32.034125", "015": "2025-05-20T14:02:34.472234", "016": "2025-05-20T14:04:29.139343", "017": "2025-05-20T14:05:54.453368", "018": "2025-05-20T14:07:20.361005", "019": "2025-05-20T14:08:30.269865", "020": "2025-05-20T14:09:26.654792", "021": "2025-05-20T14:10:48.269280", "022": "2025-05-20T14:11:55.123590", "023": "2025-05-20T14:12:28.519355", "024": "2025-05-20T14:14:46.463150", "025": "2025-05-20T14:15:31.066824", "026": "2025-05-20T14:17:19.559368", "027": "2025-05-20T14:19:00.661422", "028": "2025-05-20T14:20:41.896438", "029": "2025-05-20T14:21:28.142630", "030": "2025-05-20T14:22:18.666081", "031": "2025-05-20T14:24:45.533999", "032": "2025-05-20T14:26:03.294130", "033": "2025-05-20T14:27:58.466942", "034": "2025-05-20T14:29:15.155402", "035": "2025-05-20T14:31:14.591885", "036": "2025-05-20T14:32:19.958931", "037": "2025-05-20T14:33:58.468438", "038": "2025-05-20T14:35:48.306366", "039": "2025-05-20T14:37:37.286327", "040": "2025-05-20T14:39:02.842580", "041": "2025-05-20T14:40:06.459687", "042": "2025-05-20T14:40:59.374901", "043": "2025-05-20T14:41:46.058458", "044": "2025-05-20T14:42:36.863089", "045": "2025-05-20T14:44:11.431109", "046": "2025-05-20T14:45:07.747674", "047": "2025-05-20T14:46:14.128087", "048": "2025-05-20T14:47:38.100499", "049": "2025-05-20T14:48:56.052965", "050": "2025-05-20T14:50:41.940915", "051": "2025-05-20T14:52:07.817665", "052": "2025-05-20T14:53:17.782807", "053": "2025-05-20T14:54:18.988235", "054": "2025-05-20T14:55:06.320988", "055": "2025-05-20T14:56:04.969538", "056": "2025-05-20T14:57:56.789352", "057": "2025-05-20T14:59:04.383086", "058": "2025-05-20T15:00:55.038946", "059": "2025-05-20T15:03:02.773816", "060": "2025-05-20T15:04:51.830288", "061": "2025-05-20T15:06:15.022870", "062": "2025-05-20T15:07:54.053210", "063": "2025-05-20T15:09:26.783202", "064": "2025-05-20T15:11:36.869173", "065": "2025-05-20T15:12:39.118347", "066": "2025-05-20T15:13:39.891620", "067": "2025-05-20T15:14:41.119545", "068": "2025-05-20T15:15:42.406093", "069": "2025-05-20T15:16:32.116912", "070": "2025-05-20T15:17:30.681081", "071": "2025-05-20T15:19:01.246959", "072": "2025-05-20T15:20:37.529795", "073": "2025-05-20T15:23:29.997642", "074": "2025-05-20T15:24:45.678347", "075": "2025-05-20T15:26:12.668538", "076": "2025-05-20T15:27:59.274179", "077": "2025-05-20T15:29:46.107731", "078": "2025-05-20T15:30:56.421212", "079": "2025-05-20T15:32:15.710927", "080": "2025-05-20T15:34:37.534733", "081": "2025-05-20T15:35:46.041528", "082": "2025-05-20T15:37:22.129337", "083": "2025-05-20T15:38:44.436309", "084": "2025-05-20T15:39:47.736242", "085": "2025-05-20T15:41:30.926927", "086": "2025-05-20T15:43:23.599226", "087": "2025-05-20T15:46:19.312690", "088": "2025-05-20T15:47:54.434736", "089": "2025-05-20T15:49:15.622233", "090": "2025-05-20T15:50:27.769567", "091": "2025-05-20T15:53:13.446273", "092": "2025-05-20T15:54:37.419264", "093": "2025-05-20T15:57:08.615566", "094": "2025-05-20T16:00:17.990040", "095": "2025-05-20T16:02:57.744428", "096": "2025-05-20T16:05:28.753958", "097": "2025-05-20T16:07:57.060231", "098": "2025-05-20T16:11:01.416983", "099": "2025-05-20T16:12:42.603661"}, "trial_number": {"00": 1, "01": 2, "02": 3, "03": 4, "04": 5, "05": 6, "06": 7, "07": 8, "08": 9, "09": 10, "10": 11, "011": 12, "012": 13, "013": 14, "014": 15, "015": 16, "016": 17, "017": 18, "018": 19, "019": 20, "020": 21, "021": 22, "022": 23, "023": 24, "024": 25, "025": 26, "026": 27, "027": 28, "028": 29, "029": 30, "030": 31, "031": 32, "032": 33, "033": 34, "034": 35, "035": 36, "036": 37, "037": 38, "038": 39, "039": 40, "040": 41, "041": 42, "042": 43, "043": 44, "044": 45, "045": 46, "046": 47, "047": 48, "048": 49, "049": 50, "050": 51, "051": 52, "052": 53, "053": 54, "054": 55, "055": 56, "056": 57, "057": 58, "058": 59, "059": 60, "060": 61, "061": 62, "062": 63, "063": 64, "064": 65, "065": 66, "066": 67, "067": 68, "068": 69, "069": 70, "070": 71, "071": 72, "072": 73, "073": 74, "074": 75, "075": 76, "076": 77, "077": 78, "078": 79, "079": 80, "080": 81, "081": 82, "082": 83, "083": 84, "084": 85, "085": 86, "086": 87, "087": 88, "088": 89, "089": 90, "090": 91, "091": 92, "092": 93, "093": 94, "094": 95, "095": 96, "096": 97, "097": 98, "098": 99, "099": 100}}, "num_initial_points": null, "alpha": 0.0001, "beta": 2.6}